SlackBotter-1.2.6.data/scripts/example.py
slackbotter/__init__.py
slackbotter/bot.py
slackbotter/dictstore.py
SlackBotter-1.2.6.dist-info/LICENSE
SlackBotter-1.2.6.dist-info/METADATA
SlackBotter-1.2.6.dist-info/WHEEL
SlackBotter-1.2.6.dist-info/top_level.txt
SlackBotter-1.2.6.dist-info/RECORD
