Metadata-Version: 2.1
Name: SlackBotter
Version: 1.2.6
Summary: Slack bot for simple workflow
Home-page: http://github.com/sfinseth/SlackBotter.git
Author: Stefan Finseth
Author-email: stefanfinseth@gmail.com
License: LICENSE.txt
Platform: UNKNOWN
Requires: slackclient
Requires: requests
